dff_reset.v
`timescale 1ns/10ps

//D-flip-flop with reset
module dff_r(
    input d, clk, rst,
    output reg q, 
    output nq        );

    assign nq = ~q;

    always @(negedge clk or posedge rst) begin
        if (rst == 1) begin
            q = 0;
        end
        else begin
            q = d;
        end
    end
endmodule

module tb_dff_r;
    reg d, clk, rst;
    wire q, nq;

    dff_r dff1(d, clk, rst, q, nq);

    initial begin
        $dumpfile("tb_dff_r.vcd");
        $dumpvars(1, tb_dff_r);
            d = 0;
            clk = 0;
        #25 d = 1;
        #7  d = 0;
        #7  d = 1;
        #12 d = 0;
        #30 $finish;
    end
    
    initial fork
            rst = 0;
        #1  rst = 1;
        #4  rst = 0;
        #50 rst = 1;
        #51  rst = 0;
    join

    always begin
       #10 clk = ~clk; 
    end
endmodule

Lab1/tb_dff_r.vcd
$date
	Wed Feb 05 17:16:12 2025
$end
$version
	Icarus Verilog
$end
$timescale
	10ps
$end
$scope module tb_dff_r $end
$var wire 1 ! q $end
$var wire 1 " nq $end
$var reg 1 # clk $end
$var reg 1 $ d $end
$var reg 1 % rst $end
$upscope $end
$enddefinitions $end
$comment Show the parameter values. $end
$dumpall
$end
#0
$dumpvars
0%
0$
0#
1"
0!
$end
#100
1%
#400
0%
#1000
1#
#2000
0#
#2500
1$
#3000
1#
#3200
0$
#3900
1$
#4000
0"
1!
0#
#5000
1"
0!
1#
1%
#5100
0$
0%
