Lab1/inverter.v
`timescale 1ns/10ps

module inverter (
    input x,
    output y);

    assign y = ~x;
endmodule

inverter_delay.v
`timescale 1ns/10ps

module inverter_delay (
    input x,
    output y);
    
    assign #2 y = ~x;
endmodule

Lab1/inv_tb.v
`timescale 1ns/10ps

module tb_inv;
    reg x;
    wire y_inv, y_inv_delay;

    inverter_delay id1(x, y_inv_delay);
    inverter       i1(x, y_inv);

    initial begin
        $dumpfile("dump.vcd");
        $dumpvars(1, tb_inv);
            x = 0;
        #10 x = 1;
        #10 x = 0;
        #10 x = 1;
        #10 $finish;
    end
endmodule

Lab1/tb_inv_delay.vcd
$date
	Wed Feb 05 15:53:13 2025
$end
$version
	Icarus Verilog
$end
$timescale
	1ns
$end
$scope module tb_inv $end
$var wire 1 ! y_inv_delay $end
$var wire 1 " y_inv $end
$var reg 1 # x $end
$upscope $end
$enddefinitions $end
$comment Show the parameter values. $end
$dumpall
$end
#0
$dumpvars
0#
1"
x!
$end
#2
1!
#10
0"
1#
#12
0!
#20
1"
0#
#22
1!
#30
0"
1#
#32
0!
