Lab1/inverter.v
`timescale 1ns/10ps

module inverter (
    input x,
    output y);

    assign y = ~x;
endmodule

inverter_delay.v
`timescale 1ns/10ps

module inverter_delay (
    input x,
    output y);
    
    assign #2 y = ~x;
endmodule

Lab1/inv_tb.v
`timescale 1ns/10ps

module tb_inv;
    reg x;
    wire y_inv, y_inv_delay;

    inverter_delay id1(x, y_inv_delay);
    inverter       i1(x, y_inv);

    initial begin
        $dumpfile("dump.vcd");
        $dumpvars(1, tb_inv);
            x = 0;
        #10 x = 1;
        #10 x = 0;
        #10 x = 1;
        #10 $finish;
    end
endmodule

dff_reset.v
`timescale 1ns/10ps

//D-flip-flop with reset
module dff_r(
    input d, clk, rst,
    output reg q, 
    output nq        );

    assign nq = ~q;

    always @(negedge clk or posedge rst) begin
        if (rst == 1) begin
            q = 0;
        end
        else begin
            q = d;
        end
    end
endmodule

module tb_dff_r;
    reg d, clk, rst;
    wire q, nq;

    dff_r dff1(d, clk, rst, q, nq);

    initial begin
        $dumpfile("tb_dff_r.vcd");
        $dumpvars(1, tb_dff_r);
            d = 0;
            clk = 0;
        #25 d = 1;
        #7  d = 0;
        #7  d = 1;
        #12 d = 0;
        #30 $finish;
    end
    
    initial fork
            rst = 0;
        #1  rst = 1;
        #4  rst = 0;
        #50 rst = 1;
        #51  rst = 0;
    join

    always begin
       #10 clk = ~clk; 
    end
endmodule

Lab1/dff.v
`timescale 1ns/10ps

//D-flip-flop
module dff(
    input d, clk,
    output reg q, 
    output nq   );

    assign nq = ~q;

    always @(negedge clk) begin
        q = d;
    end
endmodule

module tb_dff;
    reg d, clk;
    wire q, nq;

    dff dff1(d, clk, q, nq);

    initial begin
        $dumpfile("tb_dff.vcd");
        $dumpvars(1, tb_dff);
        d = 0;
        clk = 0;
        #25 d = 1;
        #7 d = 0;
        #7 d = 1;
        #12 d = 0;
        #30 $finish;
    end

    always begin
       #10 clk = ~clk; 
    end
endmodule

2nand.v
`timescale 1ns/1ns

module nand2 (
    input x1, x2,
    output y    );
    
    assign y = ~(x1 & x2);
endmodule

module nand2_tb;
    reg x1, x2;
    wire y;

    nand2 nand2(x1, x2, y);

    initial begin
        $dumpfile("tb_nand2.vcd");
        $dumpvars(1, nand2_tb);
            x1 = 0;
            x2 = 0;
        #10 x1 = 1;
        #10 x1 = 0;
            x2 = 1;
        #10 x1 = 1;
            x2 = 1;
        #10 $finish;
    end
endmodule

Lab1/tb_nand2.vcd
$date
	Wed Feb 05 18:35:58 2025
$end
$version
	Icarus Verilog
$end
$timescale
	10ps
$end
$scope module nand2_tb $end
$var wire 1 ! y $end
$var reg 1 " x1 $end
$var reg 1 # x2 $end
$upscope $end
$scope module tb_dff $end
$var wire 1 $ q $end
$var wire 1 % nq $end
$var reg 1 & clk $end
$var reg 1 ' d $end
$upscope $end
$scope module tb_dff_r $end
$var wire 1 ( q $end
$var wire 1 ) nq $end
$var reg 1 * clk $end
$var reg 1 + d $end
$var reg 1 , rst $end
$upscope $end
$scope module tb_inv $end
$var wire 1 - y_inv_delay $end
$var wire 1 . y_inv $end
$var reg 1 / x $end
$upscope $end
$enddefinitions $end
$comment Show the parameter values. $end
$dumpall
$end
#0
$dumpvars
0/
1.
x-
0,
0+
0*
1)
0(
0'
0&
1%
0$
0#
0"
1!
$end
#100
1,
#200
1-
#400
0,
#1000
0.
1/
1*
1&
1"
#1200
0-
#2000
1.
0/
0*
0&
1#
0"
#2200
1-
#2500
1+
1'
#3000
0!
0.
1/
1*
1&
1"
#3200
0-
0+
0'
#3900
1+
1'
#4000
0)
0%
1(
1$
0*
0&
